README.md
setup.cfg
setup.py
pyEasyWeb3/__init__.py
pyEasyWeb3/exception.py
pyEasyWeb3.egg-info/PKG-INFO
pyEasyWeb3.egg-info/SOURCES.txt
pyEasyWeb3.egg-info/dependency_links.txt
pyEasyWeb3.egg-info/requires.txt
pyEasyWeb3.egg-info/top_level.txt
pyEasyWeb3/data/excel.py
pyEasyWeb3/metamask/metaWeb3Abi.py
pyEasyWeb3/metamask/metaWeb3Async.py
pyEasyWeb3/metamask/metaWeb3DataType.py
pyEasyWeb3/metamask/metaWeb3Main.py
pyEasyWeb3/metamask/metaWeb3Thread.py