Metadata-Version: 2.1
Name: pyEasyWeb3
Version: 1.0.4.2
Summary: library for easy web3 usage (default network BSC)
Home-page: https://github.com/onigirisell/pyEasyWeb3
Author: Fitrad3w
Author-email: onigirisell@protonmail.com
Classifier: Programming Language :: Python :: 3
Classifier: License :: OSI Approved :: MIT License
Classifier: Operating System :: OS Independent
Requires-Python: >=3.9
